{"cameraMode":{"drawMode":0,"name":"Shaded","section":"Shading Mode"},"sceneLighting":false,"audioPlay":false,"sceneViewState":{"m_AlwaysRefresh":true,"showFog":true,"showSkybox":false,"showFlares":true,"showImageEffects":true,"showParticleSystems":true,"showVisualEffectGraphs":true,"m_FxEnabled":true},"in2DMode":false,"pivot":{"x":-4.651045322418213,"y":1.2369999885559083,"z":-13.67098331451416},"rotation":{"x":-0.11032795906066895,"y":-0.851900041103363,"z":0.19896207749843598,"w":-0.4718373715877533},"size":0.1233384981751442,"orthographic":false}